amtflash/__init__.py
amtflash/amt.py
amtflash/ftdibus.py
amtflash-0.0.1.dist-info/LICENSE
amtflash-0.0.1.dist-info/METADATA
amtflash-0.0.1.dist-info/WHEEL
amtflash-0.0.1.dist-info/top_level.txt
amtflash-0.0.1.dist-info/RECORD
